[
  {
    "id": "4",
    "name": "Sejal",
    "monthly": 19360.0,
    "hourly": 92.0,
    "workingDays": 27
  },
  {
    "id": "42",
    "name": "Sarla",
    "monthly": 20640.0,
    "hourly": 52.0,
    "workingDays": 27
  },
  {
    "id": "53",
    "name": "Rekha",
    "monthly": 12000.0,
    "hourly": 67.0,
    "workingDays": 30
  },
  {
    "id": "76",
    "name": "Jayshri",
    "monthly": 14300.0,
    "hourly": 79.0,
    "workingDays": 27
  },
  {
    "id": "77",
    "name": "Payal",
    "monthly": 18150,
    "hourly": 60,
    "workingDays": 27
  },
  {
    "id": "84",
    "name": "Nanda (N)",
    "monthly": 14000,
    "hourly": 38,
    "workingDays": 27
  },
  {
    "id": "87",
    "name": "Nanda (D)",
    "monthly": 8900,
    "hourly": 49,
    "workingDays": 27
  },
  {
    "id": "96",
    "name": "Gangamasi",
    "monthly": 11500.0,
    "hourly": 48.0,
    "workingDays": 27
  },
  {
    "id": "98",
    "name": "Koki (D)",
    "monthly": 5950.0,
    "hourly": 50.0,
    "workingDays": 28
  },
  {
    "id": "102",
    "name": "Kankuben",
    "monthly": 10650.0,
    "hourly": 29.0,
    "workingDays": 30
  },
  {
    "id": "107",
    "name": "Binaben",
    "monthly": 17500.0,
    "hourly": 41.0,
    "workingDays": 30
  },
  {
    "id": "107B",
    "name": "Dimple",
    "monthly": 12650.0,
    "hourly": 52.0,
    "workingDays": 28
  },
  {
    "id": "122",
    "name": "Subhdra",
    "monthly": 13500,
    "hourly": 64,
    "workingDays": 28
  },
  {
    "id": "116",
    "name": "Neelam (Old)",
    "monthly": 13130,
    "hourly": 62,
    "workingDays": 28
  },
  {
    "id": "117",
    "name": "Maharani (Dakhuben)",
    "monthly": 9000.0,
    "hourly": 0.0,
    "workingDays": 30
  },
  {
    "id": "118",
    "name": "Khushbu didi",
    "monthly": 6800.0,
    "hourly": 0.0,
    "workingDays": 30
  },
  {
    "id": "119",
    "name": "Amrutbhai (D)",
    "monthly": 13200.0,
    "hourly": 200.0,
    "workingDays": 29
  },
  {
    "id": "119B",
    "name": "Amrutbhai (N)",
    "monthly": 12100.0,
    "hourly": 33.0,
    "workingDays": 29
  },
  {
    "id": "125",
    "name": "Harjilal",
    "monthly": 11000.0,
    "hourly": 0.0,
    "workingDays": 30
  },
  {
    "id": "126",
    "name": "Sunita",
    "monthly": 9350,
    "hourly": 51,
    "workingDays": 30
  }
]